{
    "animated": false,
    "bookmarks": 6,
    "comments": 2,
    "data_source": "UNSET",
    "dec": "60.519",
    "description": "",
    "h": 1535,
    "hash": null,
    "id": 268831,
    "imaging_cameras": [
        "QSI 583 ws"
    ],
    "imaging_telescopes": [
        "Boren Simon 10\" f2.8 Powernewton"
    ],
    "is_final": true,
    "is_solved": true,
    "license": 0,
    "license_name": "ALL_RIGHTS_RESERVED",
    "likes": 123,
    "link": "",
    "link_to_fits": "",
    "locations": [],
    "orientation": "169.543",
    "pixscale": "2.249",
    "published": "2016-10-19T20:39:49.758894",
    "ra": "44.028",
    "radius": "0.787",
    "remote_source": null,
    "resource_uri": "/api/v1/image/268831/",
    "revisions": [],
    "subjects": [
        "IC 1848",
        "IC 1871"
    ],
    "title": "ic1848",
    "updated": "2021-03-17T22:41:38.168360",
    "uploaded": "2016-10-19T21:39:49.758894",
    "url_duckduckgo": "https://www.astrobin.com/268831/0/rawthumb/duckduckgo/",
    "url_duckduckgo_small": "https://www.astrobin.com/268831/0/rawthumb/duckduckgo_small/",
    "url_gallery": "https://www.astrobin.com/268831/0/rawthumb/gallery/",
    "url_hd": "https://www.astrobin.com/268831/0/rawthumb/hd/",
    "url_histogram": "https://www.astrobin.com/268831/0/rawthumb/histogram/",
    "url_real": "https://www.astrobin.com/268831/0/rawthumb/real/",
    "url_regular": "https://www.astrobin.com/268831/0/rawthumb/regular/",
    "url_skyplot": "https://cdn.astrobin.com/images/skyplots/1119/2016/e8d678fc-c785-4598-b239-53154cc30aee.jpg",
    "url_solution": "https://cdn.astrobin.com/solutions/1119/2016/e8d678fc-c785-4598-b239-53154cc30aee-1582448993.jpg",
    "url_thumb": "https://www.astrobin.com/268831/0/rawthumb/thumb/",
    "user": "Astrobert",
    "views": 506,
    "w": 2000
}