{
    "animated": false,
    "bookmarks": 0,
    "comments": 4,
    "data_source": "UNSET",
    "dec": null,
    "description": "",
    "h": 2279,
    "hash": null,
    "id": 292601,
    "imaging_cameras": [
        "Canon EOS 7D",
        "GPU F4 Coma Corrector"
    ],
    "imaging_telescopes": [
        "Skywatcher Newton 200/800 "
    ],
    "is_final": true,
    "is_solved": false,
    "license": 0,
    "license_name": "ALL_RIGHTS_RESERVED",
    "likes": 33,
    "link": "",
    "link_to_fits": "",
    "locations": [],
    "orientation": null,
    "pixscale": null,
    "published": "2017-04-21T07:39:20.806410",
    "ra": null,
    "radius": null,
    "remote_source": null,
    "resource_uri": "/api/v1/image/292601/",
    "revisions": [
        "/api/v1/imagerevision/114694/",
        "/api/v1/imagerevision/114695/",
        "/api/v1/imagerevision/114696/",
        "/api/v1/imagerevision/114697/",
        "/api/v1/imagerevision/114698/",
        "/api/v1/imagerevision/114699/"
    ],
    "subjects": [],
    "title": "ISS Sun transit",
    "updated": "2021-03-17T21:07:29.759693",
    "uploaded": "2017-04-21T08:39:22.487354",
    "url_duckduckgo": "https://www.astrobin.com/292601/0/rawthumb/duckduckgo/",
    "url_duckduckgo_small": "https://www.astrobin.com/292601/0/rawthumb/duckduckgo_small/",
    "url_gallery": "https://www.astrobin.com/292601/0/rawthumb/gallery/",
    "url_hd": "https://www.astrobin.com/292601/0/rawthumb/hd/",
    "url_histogram": "https://www.astrobin.com/292601/0/rawthumb/histogram/",
    "url_real": "https://www.astrobin.com/292601/0/rawthumb/real/",
    "url_regular": "https://www.astrobin.com/292601/0/rawthumb/regular/",
    "url_skyplot": null,
    "url_solution": null,
    "url_thumb": "https://www.astrobin.com/292601/0/rawthumb/thumb/",
    "user": "F83eric",
    "views": 156,
    "w": 2358
}