{
    "animated": false,
    "bookmarks": 2,
    "comments": 2,
    "data_source": "UNSET",
    "dec": "-30.372",
    "description": "",
    "h": 2543,
    "hash": null,
    "id": 296405,
    "imaging_cameras": [
        "Canon 1000 Da"
    ],
    "imaging_telescopes": [
        "Canon 50 f/1.8"
    ],
    "is_final": true,
    "is_solved": true,
    "license": 0,
    "license_name": "ALL_RIGHTS_RESERVED",
    "likes": 39,
    "link": "",
    "link_to_fits": "",
    "locations": [],
    "orientation": "130.685",
    "pixscale": "22.616",
    "published": "2017-05-21T20:37:01.428806",
    "ra": "248.355",
    "radius": "14.513",
    "remote_source": null,
    "resource_uri": "/api/v1/image/296405/",
    "revisions": [],
    "subjects": [
        "IC 4592",
        "IC 4601",
        "IC 4603",
        "IC 4604",
        "IC 4605",
        "IC 4628",
        "M 4",
        "NGC 6121",
        "NGC 6281",
        "NGC 6334",
        "NGC 6357",
        "NGC 6383",
        "Part of the constellation Scorpius (Sco)",
        "The star Al Niyat (σSco)",
        "The star Antares (αSco)",
        "The star Dschubba (δSco)",
        "The star εSco",
        "The star ζ2Sco",
        "The star μ1Sco",
        "The star μ2Sco",
        "The star πSco",
        "The star ρSco",
        "The star τSco",
        "rho Oph nebula"
    ],
    "title": "RHO + Voie lactée 50mm inside",
    "updated": "2021-03-17T20:53:12.677200",
    "uploaded": "2017-05-21T21:37:02.696788",
    "url_duckduckgo": "https://www.astrobin.com/296405/0/rawthumb/duckduckgo/",
    "url_duckduckgo_small": "https://www.astrobin.com/296405/0/rawthumb/duckduckgo_small/",
    "url_gallery": "https://www.astrobin.com/296405/0/rawthumb/gallery/",
    "url_hd": "https://www.astrobin.com/296405/0/rawthumb/hd/",
    "url_histogram": "https://www.astrobin.com/296405/0/rawthumb/histogram/",
    "url_real": "https://www.astrobin.com/296405/0/rawthumb/real/",
    "url_regular": "https://www.astrobin.com/296405/0/rawthumb/regular/",
    "url_skyplot": "https://cdn.astrobin.com/images/skyplots/8519/2017/082ed49a-1443-4807-ad1e-9d3a0aeb6146.jpg",
    "url_solution": "https://cdn.astrobin.com/solutions/8519/2017/082ed49a-1443-4807-ad1e-9d3a0aeb6146-1582457707.jpg",
    "url_thumb": "https://www.astrobin.com/296405/0/rawthumb/thumb/",
    "user": "guillau012",
    "views": 129,
    "w": 3858
}