{
    "animated": false,
    "bookmarks": 8,
    "comments": 8,
    "data_source": "UNSET",
    "dec": "-48.414",
    "description": "",
    "h": 4187,
    "hash": null,
    "id": 302799,
    "imaging_cameras": [
        "Atik 314L+"
    ],
    "imaging_telescopes": [
        "Takahashi TSA102S"
    ],
    "is_final": true,
    "is_solved": true,
    "license": 0,
    "license_name": "ALL_RIGHTS_RESERVED",
    "likes": 113,
    "link": "http://quentingineys.wixsite.com/astrophoto-together",
    "link_to_fits": "",
    "locations": [],
    "orientation": "318.130",
    "pixscale": "0.391",
    "published": "2017-07-10T10:10:56.188491",
    "ra": "249.907",
    "radius": "0.381",
    "remote_source": null,
    "resource_uri": "/api/v1/image/302799/",
    "revisions": [
        "/api/v1/imagerevision/120146/",
        "/api/v1/imagerevision/120278/",
        "/api/v1/imagerevision/120288/"
    ],
    "subjects": [
        "NGC 6188"
    ],
    "title": "NGC6188 / la main de dieu",
    "updated": "2021-03-17T20:28:41.158213",
    "uploaded": "2017-07-10T11:10:57.052371",
    "url_duckduckgo": "https://www.astrobin.com/302799/0/rawthumb/duckduckgo/",
    "url_duckduckgo_small": "https://www.astrobin.com/302799/0/rawthumb/duckduckgo_small/",
    "url_gallery": "https://www.astrobin.com/302799/0/rawthumb/gallery/",
    "url_hd": "https://www.astrobin.com/302799/0/rawthumb/hd/",
    "url_histogram": "https://www.astrobin.com/302799/0/rawthumb/histogram/",
    "url_real": "https://www.astrobin.com/302799/0/rawthumb/real/",
    "url_regular": "https://www.astrobin.com/302799/0/rawthumb/regular/",
    "url_skyplot": "https://cdn.astrobin.com/images/skyplots/4753/2017/76d899fd-1602-41ea-b324-5ae62c3deb06.jpg",
    "url_solution": "https://cdn.astrobin.com/solutions/4753/2017/76d899fd-1602-41ea-b324-5ae62c3deb06-1582447615.jpg",
    "url_thumb": "https://www.astrobin.com/302799/0/rawthumb/thumb/",
    "user": "kantin",
    "views": 547,
    "w": 5629
}