{
    "animated": false,
    "bookmarks": 3,
    "comments": 14,
    "data_source": "UNSET",
    "dec": "41.264",
    "description": "* Image Acquisition by the staff at Deep Sky West Remote Observatory (www.DeepSkyWest.com).\r\n* Processing: Ruben Barbosa.\r\n* Distance: 2.65 Mly.\r\n\r\nAndromeda is a spiral galaxy located about 2.5 million light-years away from Earth in the direction of the Andromeda constellation. It is the closest to the Milky Way and can be observed with the naked eye depending on the atmospheric conditions. It is estimated to contain about 500 billion stars and is on a collision course with our galaxy. Computer simulations show that star collisions will be rare, revealing how far apart they are from each other.\r\n\r\nFrom the observation of the image, I highlight the following objects:\r\n• NGC 206, a brilliant stellar cloud and\r\n• M32 and M110, two Andromeda satellite galaxies, both ellipticals, located about 2.9 million light years.\r\n\r\n\r\nSee also:\r\n* <a href=\" http://www.astrobin.com/314942/\"> Andromeda Galaxy</a>, composition.\r\n* <a href=\"http://www.astrobin.com/312490/\"> NGC 206</a>,a Star Formation Region.\r\n* <a href=\"http://www.astrobin.com/314932/\"> M32</a>, The Smallest Messier Galaxy.\r\n* <a href=\"http://www.astrobin.com/331126/\"> M110</a>, An Elliptical Galaxy.\r\n\r\n<a href=\"http://astrob.in/314942/0/\"><img src=\"http://astrob.in/314942/0/rawthumb/gallery/get.jpg?insecure\"/></a>   <a href=\"http://astrob.in/312490/0/\"><img src=\"http://astrob.in/312490/0/rawthumb/gallery/get.jpg?insecure\"/></a>   <a href=\"http://astrob.in/314932/B/\"><img src=\"http://astrob.in/314932/B/rawthumb/gallery/get.jpg?insecure\"/></a>   <a href=\"http://astrob.in/331126/0/\"><img src=\"http://astrob.in/331126/0/rawthumb/gallery/get.jpg?insecure\"/></a>",
    "h": 3537,
    "hash": null,
    "id": 317759,
    "imaging_cameras": [
        "SBIG STX16803"
    ],
    "imaging_telescopes": [
        "Astro-Physics RH305"
    ],
    "is_final": false,
    "is_solved": true,
    "license": 0,
    "license_name": "ALL_RIGHTS_RESERVED",
    "likes": 195,
    "link": "",
    "link_to_fits": "http://deepskywest.com/giveaway/",
    "locations": [],
    "orientation": "181.631",
    "pixscale": "1.659",
    "published": "2018-01-03T13:28:35.212842",
    "ra": "10.716",
    "radius": "1.220",
    "remote_source": null,
    "resource_uri": "/api/v1/image/317759/",
    "revisions": [
        "/api/v1/imagerevision/264493/"
    ],
    "subjects": [
        "Andromeda galaxy",
        "Great Nebula in Andromeda",
        "M 110",
        "M 31",
        "M 32",
        "M110",
        "M31",
        "M32",
        "NGC 205",
        "NGC 221",
        "NGC 224",
        "NGC206"
    ],
    "title": "M31, Andromeda Galaxy (LRGB)",
    "updated": "2021-05-11T16:13:54.592145",
    "uploaded": "2017-10-21T13:23:32.546270",
    "url_duckduckgo": "https://www.astrobin.com/317759/0/rawthumb/duckduckgo/",
    "url_duckduckgo_small": "https://www.astrobin.com/317759/0/rawthumb/duckduckgo_small/",
    "url_gallery": "https://www.astrobin.com/317759/0/rawthumb/gallery/",
    "url_hd": "https://www.astrobin.com/317759/0/rawthumb/hd/",
    "url_histogram": "https://www.astrobin.com/317759/0/rawthumb/histogram/",
    "url_real": "https://www.astrobin.com/317759/0/rawthumb/real/",
    "url_regular": "https://www.astrobin.com/317759/0/rawthumb/regular/",
    "url_skyplot": "https://cdn.astrobin.com/images/skyplots/21170/2017/2768d392-1780-4b07-8b3f-a4b2ac9fa6db.png",
    "url_solution": "https://cdn.astrobin.com/solutions/21170/2017/2768d392-1780-4b07-8b3f-a4b2ac9fa6db-1582061717.png",
    "url_thumb": "https://www.astrobin.com/317759/0/rawthumb/thumb/",
    "user": "RRBBarbosa",
    "views": 571,
    "w": 3942
}