{
    "animated": false,
    "bookmarks": 0,
    "comments": 0,
    "data_source": "UNSET",
    "dec": "39.458",
    "description": "",
    "h": 1616,
    "hash": null,
    "id": 327027,
    "imaging_cameras": [
        "ZWO ASI1600MM-C"
    ],
    "imaging_telescopes": [
        "Nikon 180mm ED f/2.8"
    ],
    "is_final": true,
    "is_solved": true,
    "license": 0,
    "license_name": "ALL_RIGHTS_RESERVED",
    "likes": 31,
    "link": "",
    "link_to_fits": "",
    "locations": [
        "/api/v1/location/2808284/"
    ],
    "orientation": "202.798",
    "pixscale": "8.710",
    "published": "2017-12-25T17:03:53.345140",
    "ra": "304.798",
    "radius": "3.312",
    "remote_source": null,
    "resource_uri": "/api/v1/image/327027/",
    "revisions": [],
    "subjects": [
        "Crescent nebula",
        "IC 1318",
        "IC 4996",
        "M 29",
        "NGC 6888",
        "NGC 6910",
        "NGC 6913",
        "The star 34Cyg",
        "The star 40Cyg",
        "The star Sadr (γCyg)",
        "gamma Cyg nebula"
    ],
    "title": "Gamma Cygni and Crescent",
    "updated": "2021-03-17T18:49:43.835789",
    "uploaded": "2017-12-25T17:03:53.647581",
    "url_duckduckgo": "https://www.astrobin.com/327027/0/rawthumb/duckduckgo/",
    "url_duckduckgo_small": "https://www.astrobin.com/327027/0/rawthumb/duckduckgo_small/",
    "url_gallery": "https://www.astrobin.com/327027/0/rawthumb/gallery/",
    "url_hd": "https://www.astrobin.com/327027/0/rawthumb/hd/",
    "url_histogram": "https://www.astrobin.com/327027/0/rawthumb/histogram/",
    "url_real": "https://www.astrobin.com/327027/0/rawthumb/real/",
    "url_regular": "https://www.astrobin.com/327027/0/rawthumb/regular/",
    "url_skyplot": "https://cdn.astrobin.com/images/skyplots/images/21820/2017/3025230f-c87c-4e0f-8858-bded63a649a9.jpg",
    "url_solution": "https://cdn.astrobin.com/solutions/images/21820/2017/3025230f-c87c-4e0f-8858-bded63a649a9-1582612812.jpg",
    "url_thumb": "https://www.astrobin.com/327027/0/rawthumb/thumb/",
    "user": "ks_observer",
    "views": 82,
    "w": 2210
}