{
    "animated": false,
    "bookmarks": 3,
    "comments": 4,
    "data_source": "UNSET",
    "dec": null,
    "description": "",
    "h": 930,
    "hash": null,
    "id": 328905,
    "imaging_cameras": [
        "ASI120MM"
    ],
    "imaging_telescopes": [
        "Celestron 14\""
    ],
    "is_final": true,
    "is_solved": false,
    "license": 0,
    "license_name": "ALL_RIGHTS_RESERVED",
    "likes": 51,
    "link": "",
    "link_to_fits": "",
    "locations": [
        "/api/v1/location/2802660/"
    ],
    "orientation": null,
    "pixscale": null,
    "published": "2018-01-10T05:56:15.674078",
    "ra": null,
    "radius": null,
    "remote_source": null,
    "resource_uri": "/api/v1/image/328905/",
    "revisions": [],
    "subjects": [],
    "title": "Aristarchus - Herodotus plateau",
    "updated": "2021-03-17T16:52:08.409084",
    "uploaded": "2018-01-10T05:56:16.376868",
    "url_duckduckgo": "https://www.astrobin.com/328905/0/rawthumb/duckduckgo/",
    "url_duckduckgo_small": "https://www.astrobin.com/328905/0/rawthumb/duckduckgo_small/",
    "url_gallery": "https://www.astrobin.com/328905/0/rawthumb/gallery/",
    "url_hd": "https://www.astrobin.com/328905/0/rawthumb/hd/",
    "url_histogram": "https://www.astrobin.com/328905/0/rawthumb/histogram/",
    "url_real": "https://www.astrobin.com/328905/0/rawthumb/real/",
    "url_regular": "https://www.astrobin.com/328905/0/rawthumb/regular/",
    "url_skyplot": null,
    "url_solution": null,
    "url_thumb": "https://www.astrobin.com/328905/0/rawthumb/thumb/",
    "user": "Jordi_Delpeix_Borrell",
    "views": 216,
    "w": 1300
}