{
    "animated": false,
    "bookmarks": 0,
    "comments": 0,
    "data_source": "UNKNOWN",
    "dec": null,
    "description": "Time to start preparing for Mars opposition this summer!  Took some time off from imaging Jupiter to make some captures on Mars and Saturn on the morning of May 11, 2018.  This was the end of a fantastic week of decent seeing, that was promptly followed by a week of rains (good for processing at least...).  My Mars imaging has a way to go, but this was my first acceptable result.  Really glad that Mars will be twice as large at opposition.\r\n\r\nImaged with a C8 Evo, custom Siebert 2x barlow, ZWO ADC, and ZWO ASI224MC. Image capture using Firecapture. Stacking in AutoStakkert3 (Drizzled 1.5x). Wavelet sharpening in Registax.\r\n\r\nFireCapture v2.5  Settings\r\n------------------------------------\r\nCamera=ZWO ASI224MC\r\nFilter=RGB\r\nProfile=Mars\r\nDiameter=12.28\"\r\nMagnitude=-0.63\r\nCM=191.7°  (during mid of capture)\r\nFocalLength=4350mm (F/21)\r\nResolution=0.18\"\r\nFilename=2018-05-11-0911_1-J-RGB.avi\r\nDate=2018_05_11\r\nStart=091023.775\r\nMid=091108.780\r\nEnd=091153.786\r\nStart(UT)=091023.775\r\nMid(UT)=091108.780\r\nEnd(UT)=091153.786\r\nDuration=90.011s\r\nDate_format=yyyy_MM_dd\r\nTime_format=HHmmss\r\nLT=UT -5h\r\nFrames captured=13448\r\nFile type=AVI\r\nExtended AVI mode=true\r\nCompressed AVI=false\r\nBinning=no\r\nROI=300x262\r\nROI(Offset)=0x0\r\nFPS (avg.)=149\r\nShutter=2.501ms\r\nGain=320 (53%)\r\nUSBTraffic=100\r\nAutoExposure=off\r\nWBlue=95\r\nAutoHisto=75 (off)\r\nBrightness=1\r\nGamma=50\r\nWRed=52\r\nHardwareBin=off\r\nHighSpeed=on\r\nSoftwareGain=10 (off)\r\nHistogramm(min)=0\r\nHistogramm(max)=170\r\nHistogramm=66%\r\nNoise(avg.deviation)=n/a\r\nLimit=90 Seconds\r\nSensor temperature=25.2 °C",
    "h": 384,
    "hash": null,
    "id": 347639,
    "imaging_cameras": [
        "ASI224MC"
    ],
    "imaging_telescopes": [],
    "is_final": true,
    "is_solved": false,
    "license": 0,
    "license_name": "ALL_RIGHTS_RESERVED",
    "likes": 13,
    "link": "",
    "link_to_fits": "",
    "locations": [
        "/api/v1/location/2806888/"
    ],
    "orientation": null,
    "pixscale": null,
    "published": "2018-05-19T20:23:58.948189",
    "ra": null,
    "radius": null,
    "remote_source": null,
    "resource_uri": "/api/v1/image/347639/",
    "revisions": [],
    "subjects": [],
    "title": "Mars on May 11, 2018",
    "updated": "2021-03-17T15:26:35.295501",
    "uploaded": "2018-05-19T21:23:59.776383",
    "url_duckduckgo": "https://www.astrobin.com/347639/0/rawthumb/duckduckgo/",
    "url_duckduckgo_small": "https://www.astrobin.com/347639/0/rawthumb/duckduckgo_small/",
    "url_gallery": "https://www.astrobin.com/347639/0/rawthumb/gallery/",
    "url_hd": "https://www.astrobin.com/347639/0/rawthumb/hd/",
    "url_histogram": "https://www.astrobin.com/347639/0/rawthumb/histogram/",
    "url_real": "https://www.astrobin.com/347639/0/rawthumb/real/",
    "url_regular": "https://www.astrobin.com/347639/0/rawthumb/regular/",
    "url_skyplot": null,
    "url_solution": null,
    "url_thumb": "https://www.astrobin.com/347639/0/rawthumb/thumb/",
    "user": "JDJ",
    "views": 98,
    "w": 444
}