{
    "animated": false,
    "bookmarks": 2,
    "comments": 4,
    "data_source": "BACKYARD",
    "dec": "61.580",
    "description": "",
    "h": 3433,
    "hash": null,
    "id": 366447,
    "imaging_cameras": [
        "Canon EOS 1300D mod"
    ],
    "imaging_telescopes": [
        "Canon EF 200 mm f/2,8 L II USM - @ f/4"
    ],
    "is_final": true,
    "is_solved": true,
    "license": 0,
    "license_name": "ALL_RIGHTS_RESERVED",
    "likes": 63,
    "link": "",
    "link_to_fits": "",
    "locations": [],
    "orientation": "4.294",
    "pixscale": "4.542",
    "published": "2018-09-13T09:56:20.526635",
    "ra": "350.818",
    "radius": "3.926",
    "remote_source": null,
    "resource_uri": "/api/v1/image/366447/",
    "revisions": [],
    "subjects": [
        "1 Cas",
        "2 Cas",
        "4 Cas",
        "6 Cas",
        "Bubble nebula",
        "IC 1470",
        "IC1470",
        "M 52",
        "M52",
        "NGC 7538",
        "NGC 7635",
        "NGC 7654",
        "NGC7510",
        "NGC7538",
        "NGC7635",
        "PK110+01.1",
        "PK110-00.1",
        "PK110-01.1",
        "PK112-00.1",
        "Sh2-155",
        "Sh2-156",
        "Sh2-157",
        "Sh2-158",
        "Sh2-159",
        "Sh2-161",
        "Sh2-162",
        "Sh2-163",
        "Sh2-164",
        "Sh2-165",
        "Sh2-166",
        "The star 1Cas",
        "The star 2Cas",
        "The star 4Cas",
        "The star 6Cas"
    ],
    "title": "Messier 52 + Bubble Nebula - wide field",
    "updated": "2021-07-07T18:10:23.110185",
    "uploaded": "2018-09-13T10:56:22.751270",
    "url_duckduckgo": "https://www.astrobin.com/366447/0/rawthumb/duckduckgo/",
    "url_duckduckgo_small": "https://www.astrobin.com/366447/0/rawthumb/duckduckgo_small/",
    "url_gallery": "https://www.astrobin.com/366447/0/rawthumb/gallery/",
    "url_hd": "https://www.astrobin.com/366447/0/rawthumb/hd/",
    "url_histogram": "https://www.astrobin.com/366447/0/rawthumb/histogram/",
    "url_real": "https://www.astrobin.com/366447/0/rawthumb/real/",
    "url_regular": "https://www.astrobin.com/366447/0/rawthumb/regular/",
    "url_skyplot": "https://cdn.astrobin.com/images/skyplots/images/12571/2018/18c942af-5dd0-44f8-8ad2-17696688604c.png",
    "url_solution": "https://cdn.astrobin.com/solutions/images/12571/2018/18c942af-5dd0-44f8-8ad2-17696688604c-1582585062.png",
    "url_thumb": "https://www.astrobin.com/366447/0/rawthumb/thumb/",
    "user": "AC1000",
    "views": 108,
    "w": 5189
}