{
    "animated": false,
    "bookmarks": 4,
    "comments": 3,
    "data_source": "TRAVELLER",
    "dec": "-6.876",
    "description": "My 1 month stay in Morocco has come to and end, tomorrow I will fly back to the Netherlands. During my stay here I gathered around 100 hours of useful data and did +/- 12 objects, still much to process when I am back in the Netherlands.\r\nThis is a preview from my Witch Head Nebula, taken from excellent dark skies.\r\n\r\nWith many thanks to Hans Hoogkamer for providing me with this opportunity in general, providing the material, providing a stay and much more! Also thanks to Janina Martynaityte and her mother for providing the good care during my stay in Maroc. Could not have done this without them!",
    "h": 3370,
    "hash": null,
    "id": 384753,
    "imaging_cameras": [
        "Atik Horizon OSC"
    ],
    "imaging_telescopes": [
        "William Optics GT81 APO"
    ],
    "is_final": true,
    "is_solved": true,
    "license": 0,
    "license_name": "ALL_RIGHTS_RESERVED",
    "likes": 80,
    "link": "",
    "link_to_fits": "",
    "locations": [
        "/api/v1/location/2810186/"
    ],
    "orientation": "266.038",
    "pixscale": "2.023",
    "published": "2019-01-07T10:00:01.876384",
    "ra": "76.172",
    "radius": "1.590",
    "remote_source": null,
    "resource_uri": "/api/v1/image/384753/",
    "revisions": [],
    "subjects": [
        "65 psi Eri",
        "IC 2118",
        "IC2118",
        "NGC1797",
        "NGC1799",
        "PK205-26.1",
        "The star ψEri",
        "Witch Head nebula"
    ],
    "title": "Witch Head Nebula (Morocco - Atlas Mountains)",
    "updated": "2021-03-17T12:34:28.962139",
    "uploaded": "2019-01-07T09:50:10.808712",
    "url_duckduckgo": "https://www.astrobin.com/384753/0/rawthumb/duckduckgo/",
    "url_duckduckgo_small": "https://www.astrobin.com/384753/0/rawthumb/duckduckgo_small/",
    "url_gallery": "https://www.astrobin.com/384753/0/rawthumb/gallery/",
    "url_hd": "https://www.astrobin.com/384753/0/rawthumb/hd/",
    "url_histogram": "https://www.astrobin.com/384753/0/rawthumb/histogram/",
    "url_real": "https://www.astrobin.com/384753/0/rawthumb/real/",
    "url_regular": "https://www.astrobin.com/384753/0/rawthumb/regular/",
    "url_skyplot": "https://cdn.astrobin.com/images/skyplots/images/27015/2019/bc434bbd-9987-4fd3-9aa6-a00ea2208c72.png",
    "url_solution": "https://cdn.astrobin.com/solutions/images/27015/2019/bc434bbd-9987-4fd3-9aa6-a00ea2208c72-1582474735.png",
    "url_thumb": "https://www.astrobin.com/384753/0/rawthumb/thumb/",
    "user": "pmuskee",
    "views": 496,
    "w": 4546
}