{
    "animated": false,
    "bookmarks": 0,
    "comments": 0,
    "data_source": "BACKYARD",
    "dec": "13.103",
    "description": "",
    "h": 1429,
    "hash": null,
    "id": 387900,
    "imaging_cameras": [
        "ZWO ASI 1600MM-Cool ASI 1600MM-Cool"
    ],
    "imaging_telescopes": [
        "Williams Optics GT81 APO GTF-81 Apo Triplet"
    ],
    "is_final": true,
    "is_solved": true,
    "license": 1,
    "license_name": "ATTRIBUTION_NON_COMMERCIAL_SHARE_ALIKE",
    "likes": 9,
    "link": "",
    "link_to_fits": "",
    "locations": [
        "/api/v1/location/2810418/"
    ],
    "orientation": "5.202",
    "pixscale": "6.536",
    "published": "2019-01-26T13:41:56.120800",
    "ra": "186.800",
    "radius": "1.626",
    "remote_source": null,
    "resource_uri": "/api/v1/image/387900/",
    "revisions": [],
    "subjects": [
        "IC3258",
        "IC3280",
        "IC3303",
        "IC3305",
        "IC3311",
        "IC3331",
        "IC3344",
        "IC3349",
        "IC3355",
        "IC3363",
        "IC3382",
        "IC3388",
        "IC3393",
        "IC3432",
        "IC3443",
        "IC794",
        "M 84",
        "M 86",
        "M 87",
        "M84",
        "M86",
        "M87",
        "NGC 4374",
        "NGC 4388",
        "NGC 4402",
        "NGC 4406",
        "NGC 4413",
        "NGC 4425",
        "NGC 4435",
        "NGC 4438",
        "NGC 4459",
        "NGC 4461",
        "NGC 4473",
        "NGC 4477",
        "NGC 4486",
        "NGC4351",
        "NGC4387",
        "NGC4388",
        "NGC4402",
        "NGC4413",
        "NGC4425",
        "NGC4431",
        "NGC4435",
        "NGC4436",
        "NGC4438",
        "NGC4440",
        "NGC4446",
        "NGC4447",
        "NGC4458",
        "NGC4459",
        "NGC4461",
        "NGC4468",
        "NGC4473",
        "NGC4474",
        "NGC4476",
        "NGC4477",
        "NGC4478",
        "NGC4479",
        "The Eyes"
    ],
    "title": "Markarian's Chain",
    "updated": "2021-03-17T12:20:41.778575",
    "uploaded": "2019-01-26T13:41:56.191242",
    "url_duckduckgo": "https://www.astrobin.com/387900/0/rawthumb/duckduckgo/",
    "url_duckduckgo_small": "https://www.astrobin.com/387900/0/rawthumb/duckduckgo_small/",
    "url_gallery": "https://www.astrobin.com/387900/0/rawthumb/gallery/",
    "url_hd": "https://www.astrobin.com/387900/0/rawthumb/hd/",
    "url_histogram": "https://www.astrobin.com/387900/0/rawthumb/histogram/",
    "url_real": "https://www.astrobin.com/387900/0/rawthumb/real/",
    "url_regular": "https://www.astrobin.com/387900/0/rawthumb/regular/",
    "url_skyplot": "https://cdn.astrobin.com/images/skyplots/images/30964/2020/c71d8e55-c8d7-40f8-bfe2-a9b21fc35a7d.jpg",
    "url_solution": "https://cdn.astrobin.com/solutions/images/30964/2020/c71d8e55-c8d7-40f8-bfe2-a9b21fc35a7d-1582612677.jpg",
    "url_thumb": "https://www.astrobin.com/387900/0/rawthumb/thumb/",
    "user": "groberts",
    "views": 144,
    "w": 1080
}