{
    "animated": false,
    "bookmarks": 24,
    "comments": 40,
    "data_source": "TRAVELLER",
    "dec": "-61.562",
    "description": "This image is a four part mosaic.\r\n\r\nIt's very challenging to do mosaics using a Star Adventurer. I must do the framing by hand, using a tripod ball head. \r\n\r\nFurthermore, must confirm -in field- if all parts merge togethe properly... can be harsh, but it´ s worth it! :)",
    "h": 1825,
    "hash": null,
    "id": 400277,
    "imaging_cameras": [
        "Canon 6D modified"
    ],
    "imaging_telescopes": [
        "Canon 135mm f2"
    ],
    "is_final": false,
    "is_solved": true,
    "license": 0,
    "license_name": "ALL_RIGHTS_RESERVED",
    "likes": 235,
    "link": "https://apod.nasa.gov/apod/ap190426.html",
    "link_to_fits": "",
    "locations": [],
    "orientation": "2.384",
    "pixscale": "27.969",
    "published": "2019-04-10T14:44:15.738313",
    "ra": "176.652",
    "radius": "12.984",
    "remote_source": null,
    "resource_uri": "/api/v1/image/400277/",
    "revisions": [
        "/api/v1/imagerevision/176285/",
        "/api/v1/imagerevision/176329/"
    ],
    "subjects": [
        "IC 2602",
        "IC 2944",
        "IC 2948",
        "Mimosa (βCru)",
        "NGC 3293",
        "NGC 3372",
        "NGC 3532",
        "NGC 3572",
        "NGC 3576",
        "Part of the constellation Carina (Car)",
        "Southern Pleiades",
        "The constellation Crux (Cru)",
        "The star Becrux",
        "The star Gacrux (γCru)",
        "The star α1Cru",
        "The star α2Cru",
        "The star δCru",
        "The star εCru",
        "The star θCar",
        "The star λCen",
        "The star λMus",
        "The star πCen",
        "eta Car nebula",
        "lambda Cen nebula"
    ],
    "title": "From Southern Cross to Eta Carinae",
    "updated": "2021-06-21T12:39:56.865454",
    "uploaded": "2019-04-10T15:44:16.190520",
    "url_duckduckgo": "https://www.astrobin.com/400277/0/rawthumb/duckduckgo/",
    "url_duckduckgo_small": "https://www.astrobin.com/400277/0/rawthumb/duckduckgo_small/",
    "url_gallery": "https://www.astrobin.com/400277/0/rawthumb/gallery/",
    "url_hd": "https://www.astrobin.com/400277/0/rawthumb/hd/",
    "url_histogram": "https://www.astrobin.com/400277/0/rawthumb/histogram/",
    "url_real": "https://www.astrobin.com/400277/0/rawthumb/real/",
    "url_regular": "https://www.astrobin.com/400277/0/rawthumb/regular/",
    "url_skyplot": "https://cdn.astrobin.com/images/skyplots/029865ba-0843-467e-aeec-2b74ad4674e9.png",
    "url_solution": "https://cdn.astrobin.com/solutions/029865ba-0843-467e-aeec-2b74ad4674e9-1555023834.png",
    "url_thumb": "https://www.astrobin.com/400277/0/rawthumb/thumb/",
    "user": "kiko.fairbairn",
    "views": 2336,
    "w": 2800
}