{
    "animated": false,
    "bookmarks": 9,
    "comments": 28,
    "data_source": "BACKYARD",
    "dec": "61.382",
    "description": "This is the second time I tried to get a nice image of the center of IC 1805 (the Heart Nebula). Melotte 15 is (for my eyes) one the most interesting goals for astrophotography and shows together with these dark nebulae some wonderful details and structures. Hope you like it :-)",
    "h": 3303,
    "hash": null,
    "id": 407374,
    "imaging_cameras": [
        "Astrel Instruments AST8300"
    ],
    "imaging_telescopes": [
        "Lacerta Newton ohne Namen 250/1200"
    ],
    "is_final": true,
    "is_solved": true,
    "license": 1,
    "license_name": "ATTRIBUTION_NON_COMMERCIAL_SHARE_ALIKE",
    "likes": 213,
    "link": "http://sternwarte-wasserberg.de/",
    "link_to_fits": "",
    "locations": [
        "/api/v1/location/2808555/"
    ],
    "orientation": "358.192",
    "pixscale": "0.927",
    "published": "2019-05-26T11:38:39.186478",
    "ra": "38.489",
    "radius": "0.534",
    "remote_source": null,
    "resource_uri": "/api/v1/image/407374/",
    "revisions": [],
    "subjects": [
        "IC 1805",
        "IC1805",
        "Sh2-190"
    ],
    "title": "Melotte 15 (Bicolor)",
    "updated": "2021-03-17T10:50:26.629286",
    "uploaded": "2019-05-26T12:25:14.560748",
    "url_duckduckgo": "https://www.astrobin.com/407374/0/rawthumb/duckduckgo/",
    "url_duckduckgo_small": "https://www.astrobin.com/407374/0/rawthumb/duckduckgo_small/",
    "url_gallery": "https://www.astrobin.com/407374/0/rawthumb/gallery/",
    "url_hd": "https://www.astrobin.com/407374/0/rawthumb/hd/",
    "url_histogram": "https://www.astrobin.com/407374/0/rawthumb/histogram/",
    "url_real": "https://www.astrobin.com/407374/0/rawthumb/real/",
    "url_regular": "https://www.astrobin.com/407374/0/rawthumb/regular/",
    "url_skyplot": "https://cdn.astrobin.com/images/skyplots/images/22761/2019/cac41484-e681-46d6-b5d7-58cc43190f4c.png",
    "url_solution": "https://cdn.astrobin.com/solutions/images/22761/2019/cac41484-e681-46d6-b5d7-58cc43190f4c-1582606758.png",
    "url_thumb": "https://www.astrobin.com/407374/0/rawthumb/thumb/",
    "user": "_Frank_",
    "views": 712,
    "w": 2511
}