{
    "animated": false,
    "bookmarks": 4,
    "comments": 14,
    "data_source": "OWN_REMOTE",
    "dec": "67.332",
    "description": "",
    "h": 2027,
    "hash": null,
    "id": 416476,
    "imaging_cameras": [
        "Moravian G2-4000"
    ],
    "imaging_telescopes": [
        "ASA - Astro Systeme Austria ASA 10'"
    ],
    "is_final": false,
    "is_solved": true,
    "license": 0,
    "license_name": "ALL_RIGHTS_RESERVED",
    "likes": 70,
    "link": "",
    "link_to_fits": "",
    "locations": [
        "/api/v1/location/2799587/"
    ],
    "orientation": "173.343",
    "pixscale": "1.677",
    "published": "2019-07-21T20:48:15.324289",
    "ra": "0.987",
    "radius": "0.665",
    "remote_source": "OWN",
    "resource_uri": "/api/v1/image/416476/",
    "revisions": [
        "/api/v1/imagerevision/186362/",
        "/api/v1/imagerevision/186363/",
        "/api/v1/imagerevision/212247/"
    ],
    "subjects": [
        "NGC 7822"
    ],
    "title": "NGC 7822 (2019 version)",
    "updated": "2021-03-17T10:06:14.944010",
    "uploaded": "2019-07-21T21:48:15.480659",
    "url_duckduckgo": "https://www.astrobin.com/416476/0/rawthumb/duckduckgo/",
    "url_duckduckgo_small": "https://www.astrobin.com/416476/0/rawthumb/duckduckgo_small/",
    "url_gallery": "https://www.astrobin.com/416476/0/rawthumb/gallery/",
    "url_hd": "https://www.astrobin.com/416476/0/rawthumb/hd/",
    "url_histogram": "https://www.astrobin.com/416476/0/rawthumb/histogram/",
    "url_real": "https://www.astrobin.com/416476/0/rawthumb/real/",
    "url_regular": "https://www.astrobin.com/416476/0/rawthumb/regular/",
    "url_skyplot": "https://cdn.astrobin.com/images/skyplots/104248ea-1cb9-4df5-8f8a-1812378f45b6.jpg",
    "url_solution": "https://cdn.astrobin.com/solutions/104248ea-1cb9-4df5-8f8a-1812378f45b6-1563745993.jpg",
    "url_thumb": "https://www.astrobin.com/416476/0/rawthumb/thumb/",
    "user": "-Amenophis-",
    "views": 170,
    "w": 2012
}