{
    "animated": false,
    "bookmarks": 8,
    "comments": 12,
    "data_source": "BACKYARD",
    "dec": "69.227",
    "description": "I was lucky to add some more data and therefore improve the details captured in that fine group of galaxies.\r\n:-)\r\nIn two of those 4 nights I had good seeing with RMS values on the autoguider between 0.2 - 0.4''. The other two nights have been far worse.",
    "h": 1665,
    "hash": "795tq9",
    "id": 571320,
    "imaging_cameras": [
        "NIKON D810a"
    ],
    "imaging_telescopes": [
        "Lacerta Carbon Photonewton 254/1200"
    ],
    "is_final": false,
    "is_solved": true,
    "license": 0,
    "license_name": "ALL_RIGHTS_RESERVED",
    "likes": 185,
    "link": "",
    "link_to_fits": "",
    "locations": [
        "/api/v1/location/2805889/"
    ],
    "orientation": "1.188",
    "pixscale": "2.453",
    "published": "2021-03-05T11:52:01.611096",
    "ra": "149.573",
    "radius": "1.024",
    "remote_source": null,
    "resource_uri": "/api/v1/image/571320/",
    "revisions": [
        "/api/v1/imagerevision/276398/"
    ],
    "subjects": [
        "Bode's Galaxy",
        "Cigar Galaxy",
        "M 81",
        "M 82",
        "NGC 3031",
        "NGC 3034",
        "NGC 3077"
    ],
    "title": "M81 galaxy group",
    "updated": "2021-04-29T21:45:11.137589",
    "uploaded": "2021-03-05T11:48:38.598615",
    "url_duckduckgo": "https://www.astrobin.com/795tq9/0/rawthumb/duckduckgo/",
    "url_duckduckgo_small": "https://www.astrobin.com/795tq9/0/rawthumb/duckduckgo_small/",
    "url_gallery": "https://www.astrobin.com/795tq9/0/rawthumb/gallery/",
    "url_hd": "https://www.astrobin.com/795tq9/0/rawthumb/hd/",
    "url_histogram": "https://www.astrobin.com/795tq9/0/rawthumb/histogram/",
    "url_real": "https://www.astrobin.com/795tq9/0/rawthumb/real/",
    "url_regular": "https://www.astrobin.com/795tq9/0/rawthumb/regular/",
    "url_skyplot": "https://cdn.astrobin.com/images/skyplots/images/16772/2021/69e29426-93d4-406a-8e29-cbb18d009fe2.jpg",
    "url_solution": "https://cdn.astrobin.com/solutions/images/16772/2021/69e29426-93d4-406a-8e29-cbb18d009fe2-1614945354.jpg",
    "url_thumb": "https://www.astrobin.com/795tq9/0/rawthumb/thumb/",
    "user": "Sky-Jennersdorf",
    "views": 422,
    "w": 2500
}