{
    "animated": false,
    "bookmarks": 6,
    "comments": 3,
    "data_source": "OWN_REMOTE",
    "dec": "72.413",
    "description": null,
    "h": 4000,
    "hash": "qdawea",
    "id": 588052,
    "imaging_cameras": [
        "Finger Lakes Instruments FLI ML16803"
    ],
    "imaging_telescopes": [
        "16\" f3.75 Dream Astrograph"
    ],
    "is_final": false,
    "is_solved": true,
    "license": 0,
    "license_name": "ALL_RIGHTS_RESERVED",
    "likes": 119,
    "link": null,
    "link_to_fits": null,
    "locations": [],
    "orientation": "178.466",
    "pixscale": "1.234",
    "published": "2021-05-08T20:13:53.315532",
    "ra": "258.310",
    "radius": "0.970",
    "remote_source": "OWN",
    "resource_uri": "/api/v1/image/588052/",
    "revisions": [
        "/api/v1/imagerevision/286599/"
    ],
    "subjects": [
        "NGC 6340"
    ],
    "title": "NGC 6340",
    "updated": "2021-07-01T17:15:20.499477",
    "uploaded": "2021-05-08T20:09:35.599394",
    "url_duckduckgo": "https://www.astrobin.com/qdawea/0/rawthumb/duckduckgo/",
    "url_duckduckgo_small": "https://www.astrobin.com/qdawea/0/rawthumb/duckduckgo_small/",
    "url_gallery": "https://www.astrobin.com/qdawea/0/rawthumb/gallery/",
    "url_hd": "https://www.astrobin.com/qdawea/0/rawthumb/hd/",
    "url_histogram": "https://www.astrobin.com/qdawea/0/rawthumb/histogram/",
    "url_real": "https://www.astrobin.com/qdawea/0/rawthumb/real/",
    "url_regular": "https://www.astrobin.com/qdawea/0/rawthumb/regular/",
    "url_skyplot": "https://cdn.astrobin.com/images/skyplots/images/7344/2021/e9cdf514-eb6a-4940-9b8a-eea7b6d9fdfc.jpg",
    "url_solution": "https://cdn.astrobin.com/solutions/images/7344/2021/e9cdf514-eb6a-4940-9b8a-eea7b6d9fdfc-1620517367.jpg",
    "url_thumb": "https://www.astrobin.com/qdawea/0/rawthumb/thumb/",
    "user": "BieDie",
    "views": 214,
    "w": 4000
}