{
    "animated": false,
    "bookmarks": 2,
    "comments": 4,
    "data_source": "OWN_REMOTE",
    "dec": "36.544",
    "description": "The California Nebula is a large emission nebula that is around 1,000 light years away in the constellation of Perseus.  The nebula has an elongated shape that resembles that of California, hence the nomenclature.  \r\n\r\nThe gasses in the nebula are excited by the star Xi Persei (Menkib).\r\n\r\nThe nebula occupies around 2.5° of the night sky.  We photographed a small section of the nebula (around 0.7° x 0.56°) between 22 November 2020 and 19 January 2021.  \r\n\r\nCapture details are as follows:\r\n \r\nTelescope: TEC 140\r\nCamera: QSI 690\r\nFilters: Astrodon\r\nMount: 10 Micron GM2000HPS\r\n\r\nSII: 21 x 1200s\r\nHa: 27 x 1200s\r\nOIII: 21 x 1200s\r\n\r\nA total of 23 hours exposure.\r\n\r\nData: Steve Milne & Barry Wilson\r\nProcessing: Steve Milne",
    "h": 3344,
    "hash": "u2siwf",
    "id": 564944,
    "imaging_cameras": [
        "QSI 690 WSG-8"
    ],
    "imaging_telescopes": [
        "TEC-140"
    ],
    "is_final": true,
    "is_solved": true,
    "license": 0,
    "license_name": "ALL_RIGHTS_RESERVED",
    "likes": 119,
    "link": "https://stevemilne.smugmug.com/Photos/Sky/Nebulae/i-ZNCf7zH",
    "link_to_fits": "",
    "locations": [
        "/api/v1/location/2808075/"
    ],
    "orientation": "179.819",
    "pixscale": "0.744",
    "published": "2021-02-10T08:55:53.031087",
    "ra": "60.237",
    "radius": "0.442",
    "remote_source": "eEyE",
    "resource_uri": "/api/v1/image/564944/",
    "revisions": [],
    "subjects": [],
    "title": "California Nebula Detail",
    "updated": "2021-04-05T15:29:20.621561",
    "uploaded": "2021-02-10T08:46:59.274037",
    "url_duckduckgo": "https://www.astrobin.com/u2siwf/0/rawthumb/duckduckgo/",
    "url_duckduckgo_small": "https://www.astrobin.com/u2siwf/0/rawthumb/duckduckgo_small/",
    "url_gallery": "https://www.astrobin.com/u2siwf/0/rawthumb/gallery/",
    "url_hd": "https://www.astrobin.com/u2siwf/0/rawthumb/hd/",
    "url_histogram": "https://www.astrobin.com/u2siwf/0/rawthumb/histogram/",
    "url_real": "https://www.astrobin.com/u2siwf/0/rawthumb/real/",
    "url_regular": "https://www.astrobin.com/u2siwf/0/rawthumb/regular/",
    "url_skyplot": "https://cdn.astrobin.com/images/skyplots/images/10769/2021/0819972b-7257-472d-8771-96e6261439a3.jpg",
    "url_solution": "https://cdn.astrobin.com/solutions/images/10769/2021/0819972b-7257-472d-8771-96e6261439a3-1613052838.jpg",
    "url_thumb": "https://www.astrobin.com/u2siwf/0/rawthumb/thumb/",
    "user": "gnomus",
    "views": 179,
    "w": 2672
}