{
    "animated": false,
    "bookmarks": 0,
    "comments": 0,
    "data_source": "BACKYARD",
    "dec": null,
    "description": "chromospheric magma ( 28.09.2014)\r\n6 years ago a large solar activity around AR2172-2173\r\n\r\nRéfractor 230mm H-Alpha",
    "h": 1084,
    "hash": "ysi1t0",
    "id": 528460,
    "imaging_cameras": [
        "Basler acA1920-155um"
    ],
    "imaging_telescopes": [
        "Istar Optical refractor 230 mm F/D 9 Anastigmatic Special H-Alpha R30"
    ],
    "is_final": true,
    "is_solved": false,
    "license": 0,
    "license_name": "ALL_RIGHTS_RESERVED",
    "likes": 73,
    "link": "",
    "link_to_fits": "",
    "locations": [],
    "orientation": null,
    "pixscale": null,
    "published": "2020-09-29T05:05:56.646457",
    "ra": null,
    "radius": null,
    "remote_source": null,
    "resource_uri": "/api/v1/image/528460/",
    "revisions": [],
    "subjects": [],
    "title": "chromospheric magma ( 29.09.2014) AR2172-2173",
    "updated": "2021-03-16T19:40:00.667383",
    "uploaded": "2020-09-29T06:01:23.304656",
    "url_duckduckgo": "https://www.astrobin.com/ysi1t0/0/rawthumb/duckduckgo/",
    "url_duckduckgo_small": "https://www.astrobin.com/ysi1t0/0/rawthumb/duckduckgo_small/",
    "url_gallery": "https://www.astrobin.com/ysi1t0/0/rawthumb/gallery/",
    "url_hd": "https://www.astrobin.com/ysi1t0/0/rawthumb/hd/",
    "url_histogram": "https://www.astrobin.com/ysi1t0/0/rawthumb/histogram/",
    "url_real": "https://www.astrobin.com/ysi1t0/0/rawthumb/real/",
    "url_regular": "https://www.astrobin.com/ysi1t0/0/rawthumb/regular/",
    "url_skyplot": null,
    "url_solution": null,
    "url_thumb": "https://www.astrobin.com/ysi1t0/0/rawthumb/thumb/",
    "user": "jp-brahic",
    "views": 172,
    "w": 1900
}