{
    "animated": false,
    "bookmarks": 2,
    "comments": 0,
    "data_source": "BACKYARD",
    "dec": "34.248",
    "description": "",
    "h": 2840,
    "hash": "zenu69",
    "id": 559003,
    "imaging_cameras": [
        "ZWO Optical ASI1600MM-Cool"
    ],
    "imaging_telescopes": [
        "TPO RC10 RC 10 f/8"
    ],
    "is_final": true,
    "is_solved": true,
    "license": 0,
    "license_name": "ALL_RIGHTS_RESERVED",
    "likes": 20,
    "link": "",
    "link_to_fits": "",
    "locations": [
        "/api/v1/location/2805492/"
    ],
    "orientation": "176.972",
    "pixscale": "0.389",
    "published": "2021-01-17T19:43:04.058358",
    "ra": "82.861",
    "radius": "0.256",
    "remote_source": null,
    "resource_uri": "/api/v1/image/559003/",
    "revisions": [],
    "subjects": [
        "NGC 1931",
        "NGC1931",
        "Sh2-237"
    ],
    "title": "NGC1931 Fly Nebula",
    "updated": "2021-04-07T21:19:09.469696",
    "uploaded": "2021-01-17T19:16:14.612653",
    "url_duckduckgo": "https://www.astrobin.com/zenu69/0/rawthumb/duckduckgo/",
    "url_duckduckgo_small": "https://www.astrobin.com/zenu69/0/rawthumb/duckduckgo_small/",
    "url_gallery": "https://www.astrobin.com/zenu69/0/rawthumb/gallery/",
    "url_hd": "https://www.astrobin.com/zenu69/0/rawthumb/hd/",
    "url_histogram": "https://www.astrobin.com/zenu69/0/rawthumb/histogram/",
    "url_real": "https://www.astrobin.com/zenu69/0/rawthumb/real/",
    "url_regular": "https://www.astrobin.com/zenu69/0/rawthumb/regular/",
    "url_skyplot": "https://cdn.astrobin.com/images/skyplots/images/17704/2021/4dac214d-e74a-4cd5-8851-6f44b728a234.tiff",
    "url_solution": "https://cdn.astrobin.com/solutions/images/17704/2021/4dac214d-e74a-4cd5-8851-6f44b728a234-1610911671.tiff",
    "url_thumb": "https://www.astrobin.com/zenu69/0/rawthumb/thumb/",
    "user": "Phitchco",
    "views": 59,
    "w": 3786
}